python_sdk_local/__init__.py
python_sdk_local/constants.py
python_sdk_local/http_response.py
python_sdk_local/item.py
python_sdk_local/our_object.py
python_sdk_local/service_response.py
python_sdk_local/unified_json.py
python_sdk_local/utilities.py
python_sdk_local/valid_json_versions.py
python_sdk_local/validate_environment.py
python_sdk_local-0.0.154.dist-info/METADATA
python_sdk_local-0.0.154.dist-info/WHEEL
python_sdk_local-0.0.154.dist-info/top_level.txt
python_sdk_local-0.0.154.dist-info/RECORD
