Metadata-Version: 2.4
Name: python-sdk-local
Version: 0.0.154
Summary: PyPI Package for Circles Python SDK Local Python
Home-page: https://github.com/circles-zone/python-sdk-local-python-package
Author: Circles
Author-email: info@circlez.ai
Classifier: Programming Language :: Python :: 3
Classifier: License :: Other/Proprietary License
Classifier: Operating System :: OS Independent
Requires-Dist: requests
Requires-Dist: python-dotenv
Requires-Dist: pyjwt
Requires-Dist: python-sdk-remote
Requires-Dist: user-context-remote
Dynamic: author
Dynamic: author-email
Dynamic: classifier
Dynamic: description
Dynamic: description-content-type
Dynamic: home-page
Dynamic: requires-dist
Dynamic: summary
